groqqy/__init__.py
groqqy/agent.py
groqqy/bot.py
groqqy/cli.py
groqqy/config.py
groqqy/log.py
groqqy/provider.py
groqqy/strategy.py
groqqy/tool.py
groqqy/tools.py
groqqy/utils.py
groqqy/components/__init__.py
groqqy/components/conversation.py
groqqy/components/executor.py
groqqy/components/exporter.py
groqqy/components/tracker.py
groqqy/providers/__init__.py
groqqy/providers/groq.py
groqqy-2.3.0.dist-info/licenses/LICENSE
groqqy-2.3.0.dist-info/METADATA
groqqy-2.3.0.dist-info/WHEEL
groqqy-2.3.0.dist-info/entry_points.txt
groqqy-2.3.0.dist-info/top_level.txt
groqqy-2.3.0.dist-info/RECORD
