Metadata-Version: 2.4
Name: groqqy
Version: 2.3.0
Summary: Clean, composable micro agentic bot powered by Groq
Author-email: Scott Sen <scott@example.com>
License: MIT
Project-URL: Homepage, https://github.com/scottsen/groqqy
Project-URL: Documentation, https://github.com/scottsen/groqqy/tree/master/docs
Project-URL: Repository, https://github.com/scottsen/groqqy
Project-URL: Issues, https://github.com/scottsen/groqqy/issues
Keywords: ai,agents,groq,llm,agentic,tool-calling,react
Classifier: Development Status :: 4 - Beta
Classifier: Intended Audience :: Developers
Classifier: Intended Audience :: Education
Classifier: License :: OSI Approved :: MIT License
Classifier: Programming Language :: Python :: 3
Classifier: Programming Language :: Python :: 3.8
Classifier: Programming Language :: Python :: 3.9
Classifier: Programming Language :: Python :: 3.10
Classifier: Programming Language :: Python :: 3.11
Classifier: Programming Language :: Python :: 3.12
Classifier: Topic :: Scientific/Engineering :: Artificial Intelligence
Classifier: Topic :: Software Development :: Libraries :: Python Modules
Requires-Python: >=3.8
License-File: LICENSE
Requires-Dist: requests>=2.31.0
Requires-Dist: loguru>=0.7.0
Provides-Extra: dev
Requires-Dist: pytest>=7.0.0; extra == "dev"
Requires-Dist: pytest-cov>=4.0.0; extra == "dev"
Requires-Dist: mypy>=1.0.0; extra == "dev"
Requires-Dist: black>=23.0.0; extra == "dev"
Requires-Dist: flake8>=6.0.0; extra == "dev"
Dynamic: license-file
